import_toolbox/__init__.py
import_toolbox/windpro/import_windpro_decibel.py
import_toolbox/windpro/import_windpro_nord2000.py
import_toolbox/windpro/import_windpro_topography.py
import_toolbox-0.0.5.dist-info/METADATA
import_toolbox-0.0.5.dist-info/WHEEL
import_toolbox-0.0.5.dist-info/RECORD
